README.md
setup.py
Adafruit_BluefruitLE/__init__.py
Adafruit_BluefruitLE/config.py
Adafruit_BluefruitLE/platform.py
Adafruit_BluefruitLE/bleak_dbus/__init__.py
Adafruit_BluefruitLE/bleak_dbus/adapter.py
Adafruit_BluefruitLE/bleak_dbus/device.py
Adafruit_BluefruitLE/bleak_dbus/gatt.py
Adafruit_BluefruitLE/bleak_dbus/provider.py
Adafruit_BluefruitLE/bluez_dbus/__init__.py
Adafruit_BluefruitLE/bluez_dbus/adapter.py
Adafruit_BluefruitLE/bluez_dbus/device.py
Adafruit_BluefruitLE/bluez_dbus/gatt.py
Adafruit_BluefruitLE/bluez_dbus/provider.py
Adafruit_BluefruitLE/corebluetooth/__init__.py
Adafruit_BluefruitLE/corebluetooth/adapter.py
Adafruit_BluefruitLE/corebluetooth/device.py
Adafruit_BluefruitLE/corebluetooth/gatt.py
Adafruit_BluefruitLE/corebluetooth/metadata.py
Adafruit_BluefruitLE/corebluetooth/objc_helpers.py
Adafruit_BluefruitLE/corebluetooth/provider.py
Adafruit_BluefruitLE/interfaces/__init__.py
Adafruit_BluefruitLE/interfaces/adapter.py
Adafruit_BluefruitLE/interfaces/device.py
Adafruit_BluefruitLE/interfaces/gatt.py
Adafruit_BluefruitLE/interfaces/provider.py
Adafruit_BluefruitLE/services/__init__.py
Adafruit_BluefruitLE/services/colorific.py
Adafruit_BluefruitLE/services/device_information.py
Adafruit_BluefruitLE/services/servicebase.py
Adafruit_BluefruitLE/services/uart.py
bluebrick_Adafruit_BluefruitLE.egg-info/PKG-INFO
bluebrick_Adafruit_BluefruitLE.egg-info/SOURCES.txt
bluebrick_Adafruit_BluefruitLE.egg-info/dependency_links.txt
bluebrick_Adafruit_BluefruitLE.egg-info/requires.txt
bluebrick_Adafruit_BluefruitLE.egg-info/top_level.txt