Metadata-Version: 1.0
Name: bluebrick-Adafruit-BluefruitLE
Version: 0.9.13
Summary: Fork of Python library for interacting with Bluefruit LE (Bluetooth low energy) devices on Linux or OSX.
Home-page: https://github.com/virantha/Adafruit_Python_BluefruitLE/
Author: Virantha Ekanayake
Author-email: virantha@gmail.com
License: MIT
Platform: UNKNOWN
